page/__init__.py
page/gen.py
page/imports.py
page/models.py
page/static.py
page/tests.py
page/templates/page/amp-boilerplate.html
page/templates/page/base.html
page/templates/page/feed.xml
page/templates/page/nav.html
page/templates/page/page.html
page/templates/page/sitemap.xml
page/templates/shop/README.md
page/templates/shop/base.html
page/templates/shop/cart.html
page/templates/shop/cart.js.html
page/templates/shop/order.htm
page/templates/shop/order.php
page/templates/shop/page.html
page/templates/shop/_assets/config.js
page/templates/shop/_assets/lang.js
page/templates/shop/_assets/order.js
page/templates/shop/_assets/shop.js
page/templates/shop/_assets/test-products.csv
page-0.2.1.dist-info/METADATA
page-0.2.1.dist-info/WHEEL
page-0.2.1.dist-info/entry_points.txt
page-0.2.1.dist-info/licenses/LICENSE
page-0.2.1.dist-info/RECORD
