Metadata-Version: 2.3
Name: page
Version: 0.2.1
Summary: Static website generator
Project-URL: Funding, https://unilexicon.com/fm/pay.html
Author-email: "F. Malina" <fmalina@pm.me>
License: BSD License
Keywords: CMS,static
Classifier: Development Status :: 5 - Production/Stable
Classifier: Intended Audience :: Developers
Classifier: Intended Audience :: Information Technology
Classifier: License :: OSI Approved :: BSD License
Classifier: Programming Language :: Python :: 3
Classifier: Topic :: Documentation
Classifier: Topic :: Internet :: WWW/HTTP :: Dynamic Content :: Content Management System
Classifier: Topic :: Internet :: WWW/HTTP :: Dynamic Content :: News/Diary
Requires-Python: >=3.9
Requires-Dist: brotli
Requires-Dist: click
Requires-Dist: jinja2
Requires-Dist: markdown2
Requires-Dist: markupsafe
Requires-Dist: pyyaml
Provides-Extra: dev
Requires-Dist: django; extra == 'dev'
Requires-Dist: lxml; extra == 'dev'
Requires-Dist: markdownify; extra == 'dev'
Requires-Dist: pymysql; extra == 'dev'
Requires-Dist: sqlalchemy; extra == 'dev'
